<annotation>
	<folder />
	<filename>obstaclemarque_505af29b-06c6-4dae-9bf8-f7076621012e_jpg.rf.a2024ea2f9face4070289330cb0ad168.jpg</filename>
	<path>obstaclemarque_505af29b-06c6-4dae-9bf8-f7076621012e_jpg.rf.a2024ea2f9face4070289330cb0ad168.jpg</path>
	<source>
		<database>roboflow.com</database>
	</source>
	<size>
		<width>640</width>
		<height>640</height>
		<depth>3</depth>
	</size>
	<segmented>0</segmented>
	<object>
		<name>marque</name>
		<pose>Unspecified</pose>
		<truncated>0</truncated>
		<difficult>0</difficult>
		<occluded>0</occluded>
		<bndbox>
			<xmin>1</xmin>
			<xmax>255</xmax>
			<ymin>25</ymin>
			<ymax>431</ymax>
		</bndbox>
	</object>
</annotation>